{"cameraMode":{"drawMode":0,"name":"Shaded","section":"Shading Mode"},"sceneLighting":false,"audioPlay":false,"sceneViewState":{"m_AlwaysRefresh":false,"showFog":true,"showSkybox":false,"showFlares":true,"showImageEffects":true,"showParticleSystems":true,"showVisualEffectGraphs":true,"m_FxEnabled":true},"in2DMode":false,"pivot":{"x":0.0,"y":0.24941295385360719,"z":0.0},"rotation":{"x":-0.1035914197564125,"y":-0.028077373281121255,"z":0.0027912629302591087,"w":-0.9942949414253235},"size":3.7560696601867677,"orthographic":false}